Metadata-Version: 1.0
Name: yg.thumpy
Version: 1.0.1
Summary: A Python web server that uses Pillow to dynamically scale, crop, transform and serve images from S3 or the local filesystem
Home-page: https://github.com/yougov/yg.thumpy
Author: YouGov, Plc.
Author-email: dev@yougov.com
License: UNKNOWN
Platform: UNKNOWN
